realpoetry/__init__.py
realpoetry/validator.py
realpoetry-0.1.0.dist-info/METADATA
realpoetry-0.1.0.dist-info/WHEEL
realpoetry-0.1.0.dist-info/RECORD
